headerz/__init__.py
headerz-0.1.dist-info/LICENSE
headerz-0.1.dist-info/METADATA
headerz-0.1.dist-info/WHEEL
headerz-0.1.dist-info/top_level.txt
headerz-0.1.dist-info/RECORD
