Metadata-Version: 2.1
Name: headerz
Version: 0.1
Summary: A simple package for parsing a header string from sniffer app An android/browser on PC
Home-page: https://github.com/karjok/headerz
Author: Karjok Pangesty
Author-email: karjok.pangesty@gmail.com
License: MIT
Download-URL: https://github.com/karjok/headerz/archive/v_01.tar.gz
Keywords: header parser,header string,parsing header string
Platform: UNKNOWN
Classifier: Development Status :: 3 - Alpha
Classifier: Intended Audience :: Developers
Classifier: Topic :: Software Development :: Build Tools
Classifier: License :: OSI Approved :: MIT License
Classifier: Programming Language :: Python :: 3
